pgconsole/__init__.py
pgconsole-0.1.2.dist-info/licenses/LICENSE
pgconsole-0.1.2.dist-info/METADATA
pgconsole-0.1.2.dist-info/WHEEL
pgconsole-0.1.2.dist-info/top_level.txt
pgconsole-0.1.2.dist-info/RECORD
