Metadata-Version: 2.4
Name: pgconsole
Version: 0.1.2
Summary: A Python library to add full-featured console to any game.
Author: xdoko01
License: MIT
Project-URL: Homepage, https://github.com/xdoko01/Pygame-Console
Project-URL: Issues, https://github.com/xdoko01/Pygame-Console/issues
Requires-Python: >=3.7
License-File: LICENSE
Requires-Dist: pygame-ce
Requires-Dist: pathlib
Requires-Dist: pgbitmapfont>=0.1.5
Dynamic: license-file
